{
    "Ar36": {
        "error": 0.00016323108196002707,
        "error_type": "SEM",
        "filter_outliers_dict": {
            "filter_outliers": true,
            "iterations": 1,
            "std_devs": 2
        },
        "fit": "Parabolic",
        "fn": 268,
        "include_baseline_error": false,
        "n": 280,
        "reviewed": true,
        "value": 0.0021804432454303646
    },
    "Ar37": {
        "error": 0.005639735353293682,
        "error_type": "SEM",
        "filter_outliers_dict": {
            "filter_outliers": true,
            "iterations": 1,
            "std_devs": 2
        },
        "fit": "Linear",
        "fn": 268,
        "include_baseline_error": false,
        "n": 280,
        "reviewed": true,
        "value": 0.07559461390382238
    },
    "Ar38": {
        "error": 0.0025074067454676414,
        "error_type": "SEM",
        "filter_outliers_dict": {
            "filter_outliers": true,
            "iterations": 1,
            "std_devs": 2
        },
        "fit": "Linear",
        "fn": 269,
        "include_baseline_error": false,
        "n": 280,
        "reviewed": true,
        "value": 0.021985119732508822
    },
    "Ar39": {
        "error": 0.013577575919437914,
        "error_type": "SEM",
        "filter_outliers_dict": {
            "filter_outliers": true,
            "iterations": 1,
            "std_devs": 2
        },
        "fit": "Parabolic",
        "fn": 267,
        "include_baseline_error": false,
        "n": 280,
        "reviewed": true,
        "value": -0.1421432874642815
    },
    "Ar40": {
        "error": 0.009328184314088052,
        "error_type": "SEM",
        "filter_outliers_dict": {
            "filter_outliers": true,
            "iterations": 1,
            "std_devs": 2
        },
        "fit": "Parabolic",
        "fn": 266,
        "include_baseline_error": false,
        "n": 280,
        "reviewed": true,
        "value": 0.1705741816155165
    },
    "Ar41": {
        "error": 0.0033514452517827403,
        "error_type": "SEM",
        "filter_outliers_dict": {
            "filter_outliers": true,
            "iterations": 1,
            "std_devs": 2
        },
        "fit": "linear",
        "value": -0.05462063069375103
    }
}