{
    "AX": {
        "error": 0.007315623673113302,
        "error_type": "SEM",
        "filter_outliers_dict": {
            "filter_outliers": true,
            "iterations": 1,
            "std_devs": 2
        },
        "fit": "Average",
        "fn": 42,
        "include_baseline_error": false,
        "n": 45,
        "reviewed": true,
        "value": -0.14680798378373897
    },
    "CDD": {
        "error": 2.5628996104181258e-05,
        "error_type": "SEM",
        "filter_outliers_dict": {
            "filter_outliers": true,
            "iterations": 1,
            "std_devs": 10
        },
        "fit": "Average",
        "fn": 45,
        "include_baseline_error": false,
        "n": 45,
        "reviewed": true,
        "value": 0.0001664703356153849
    },
    "H1": {
        "error": 0.006997201326475444,
        "error_type": "SEM",
        "filter_outliers_dict": {
            "filter_outliers": true,
            "iterations": 1,
            "std_devs": 2
        },
        "fit": "Average",
        "fn": 45,
        "include_baseline_error": false,
        "n": 45,
        "reviewed": true,
        "value": 0.045140713329116504
    },
    "H2": {
        "error": 0.007021729939472727,
        "error_type": "SEM",
        "filter_outliers_dict": {
            "filter_outliers": true,
            "iterations": 1,
            "std_devs": 2
        },
        "fit": "average",
        "value": -0.030769314141233964
    },
    "L1": {
        "error": 0.005526652297409941,
        "error_type": "SEM",
        "filter_outliers_dict": {
            "filter_outliers": true,
            "iterations": 1,
            "std_devs": 2
        },
        "fit": "Average",
        "fn": 42,
        "include_baseline_error": false,
        "n": 45,
        "reviewed": true,
        "value": 0.024075175525337857
    },
    "L2": {
        "error": 0.006898337796707391,
        "error_type": "SEM",
        "filter_outliers_dict": {
            "filter_outliers": true,
            "iterations": 1,
            "std_devs": 2
        },
        "fit": "Average",
        "fn": 44,
        "include_baseline_error": false,
        "n": 45,
        "reviewed": true,
        "value": 0.036050719685259865
    }
}