{
    "Ar36": {
        "error": 0.0012358157024577228,
        "error_type": "SEM",
        "filter_outliers_dict": {
            "filter_outliers": true,
            "iterations": 1,
            "std_devs": 2
        },
        "fit": "Linear",
        "value": 0.2083632361823859
    },
    "Ar37": {
        "error": 0.011335707192702263,
        "error_type": "SEM",
        "filter_outliers_dict": {
            "filter_outliers": true,
            "iterations": 1,
            "std_devs": 2
        },
        "fit": "linear",
        "value": 0.08842409729633627
    },
    "Ar38": {
        "error": 0.003940697004706559,
        "error_type": "SEM",
        "filter_outliers_dict": {
            "filter_outliers": true,
            "iterations": 1,
            "std_devs": 2
        },
        "fit": "linear",
        "value": 0.7348689771530025
    },
    "Ar39": {
        "error": 0.019132137126954198,
        "error_type": "SEM",
        "filter_outliers_dict": {
            "filter_outliers": true,
            "iterations": 1,
            "std_devs": 2
        },
        "fit": "Linear",
        "value": 57.49678499734508
    },
    "Ar40": {
        "error": 0.04739263387914927,
        "error_type": "SEM",
        "filter_outliers_dict": {
            "filter_outliers": true,
            "iterations": 1,
            "std_devs": 2
        },
        "fit": "Linear",
        "value": 776.1026446038504
    },
    "Ar41": {
        "error": 0.002356428461773367,
        "error_type": "SEM",
        "filter_outliers_dict": {
            "filter_outliers": true,
            "iterations": 1,
            "std_devs": 2
        },
        "fit": "Average",
        "value": -0.03815224880972657
    }
}