{
    "AX": {
        "error": 0.00700140528970435,
        "error_type": "SEM",
        "filter_outliers_dict": {
            "filter_outliers": true,
            "iterations": 1,
            "std_devs": 2
        },
        "fit": "Average",
        "fn": 42,
        "include_baseline_error": false,
        "n": 45,
        "reviewed": true,
        "value": -0.1418943102693274
    },
    "CDD": {
        "error": 9.219066503182677e-06,
        "error_type": "SEM",
        "filter_outliers_dict": {
            "filter_outliers": true,
            "iterations": 1,
            "std_devs": 10
        },
        "fit": "Average",
        "fn": 45,
        "include_baseline_error": false,
        "n": 45,
        "reviewed": true,
        "value": 2.0384123005593816e-05
    },
    "H1": {
        "error": 0.006602002461571142,
        "error_type": "SEM",
        "filter_outliers_dict": {
            "filter_outliers": true,
            "iterations": 1,
            "std_devs": 2
        },
        "fit": "Average",
        "fn": 45,
        "include_baseline_error": false,
        "n": 45,
        "reviewed": true,
        "value": 0.01710725883862728
    },
    "H2": {
        "error": 0.004875600937546604,
        "error_type": "SEM",
        "filter_outliers_dict": {
            "filter_outliers": true,
            "iterations": 1,
            "std_devs": 2
        },
        "fit": "average",
        "value": -0.021224581306977006
    },
    "L1": {
        "error": 0.005631657994585888,
        "error_type": "SEM",
        "filter_outliers_dict": {
            "filter_outliers": true,
            "iterations": 1,
            "std_devs": 2
        },
        "fit": "Average",
        "fn": 43,
        "include_baseline_error": false,
        "n": 45,
        "reviewed": true,
        "value": -0.006177759527629458
    },
    "L2": {
        "error": 0.005714879158771333,
        "error_type": "SEM",
        "filter_outliers_dict": {
            "filter_outliers": true,
            "iterations": 1,
            "std_devs": 2
        },
        "fit": "Average",
        "fn": 42,
        "include_baseline_error": false,
        "n": 45,
        "reviewed": true,
        "value": 0.031973505279027106
    }
}